quant23rg/__init__.py
quant23rg/implied_volatility.py
quant23rg/pricingBS.py
quant23rg/pricingCallEuropBS.py
quant23rg/pricingGBM.py
quant23rg/pricingPutEuropBS.py
quant23rg/riskManagement.py
quant23rg-0.0.5.dist-info/LICENSE
quant23rg-0.0.5.dist-info/METADATA
quant23rg-0.0.5.dist-info/WHEEL
quant23rg-0.0.5.dist-info/top_level.txt
quant23rg-0.0.5.dist-info/RECORD
