Metadata-Version: 2.1
Name: quant23rg
Version: 0.0.5
Summary: Package for quantitative analysis
Author-email: Adrien Calas <le23rg@icloud.com>
Project-URL: Homepage, https://github.com/leRayGorbella/quant23rg
Project-URL: Bug Tracker, https://github.com/leRayGorbella/quant23rg/issues
Classifier: Programming Language :: Python :: 3
Classifier: License :: OSI Approved :: MIT License
Classifier: Operating System :: OS Independent
Requires-Python: >=3.7
License-File: LICENSE
